reproducibly.py
reproducibly-0.0.20.dist-info/METADATA
reproducibly-0.0.20.dist-info/WHEEL
reproducibly-0.0.20.dist-info/entry_points.txt
reproducibly-0.0.20.dist-info/RECORD
