Metadata-Version: 2.4
Name: reproducibly
Version: 0.0.20
Summary: Reproducibly build Python packages.
Author-email: Keith Maxwell <keith.maxwell@gmail.com>
Requires-Python: >=3.13
License-Expression: MPL-2.0
Classifier: Programming Language :: Python :: 3
Requires-Dist: build==1.4.0
Requires-Dist: cibuildwheel==3.3.1
Requires-Dist: packaging==26.0
Requires-Dist: pyproject-hooks==1.2.0
Project-URL: Homepage, https://github.com/maxwell-k/reproducibly/
Project-URL: Issues, https://github.com/maxwell-k/reproducibly/issues
